pylibgen/__init__.py
pylibgen/constants.py
pylibgen/exceptions.py
pylibgen/pylibgen.py
pylibgen-2.0.2.dist-info/LICENSE
pylibgen-2.0.2.dist-info/METADATA
pylibgen-2.0.2.dist-info/WHEEL
pylibgen-2.0.2.dist-info/top_level.txt
pylibgen-2.0.2.dist-info/RECORD
