Metadata-Version: 2.1
Name: pylibgen
Version: 2.0.2
Summary: Python interface to Library Genesis.
Home-page: https://github.com/JoshuaRLi/pylibgen
Author: Joshua Li
Author-email: josh@jrl.ninja
Maintainer: Joshua Li
Maintainer-email: josh@jrl.ninja
License: MIT
Download-URL: https://github.com/JoshuaRLi/pylibgen/archive/v2.0.2.tar.gz
Keywords: libgen,library,genesis,search,download,books,ebooks,textbooks
Platform: UNKNOWN
Classifier: Development Status :: 7 - Inactive
Classifier: Intended Audience :: Developers
Classifier: Topic :: Software Development
Classifier: Natural Language :: English
Classifier: License :: OSI Approved :: MIT License
Classifier: Programming Language :: Python
Classifier: Programming Language :: Python :: 3 :: Only
Classifier: Programming Language :: Python :: 3.6
Classifier: Programming Language :: Python :: 3.7
Requires-Python: >=3.6
Requires-Dist: requests (==2.22.0)
Provides-Extra: dev
Requires-Dist: pre-commit (==1.16.*) ; extra == 'dev'
Requires-Dist: pytest (==4.*) ; extra == 'dev'
